{
    "data": [
        {
            "height": -0.44648171222927246,
            "time": "2025-05-07T00:58:00+00:00",
            "type": "low"
        },
        {
            "height": 0.44538852396305495,
            "time": "2025-05-07T07:18:00+00:00",
            "type": "high"
        },
        {
            "height": -0.2787455617620912,
            "time": "2025-05-07T13:14:00+00:00",
            "type": "low"
        },
        {
            "height": 0.4884849167294262,
            "time": "2025-05-07T19:12:00+00:00",
            "type": "high"
        },
        {
            "height": -0.45629878200273055,
            "time": "2025-05-08T01:33:00+00:00",
            "type": "low"
        },
        {
            "height": 0.5369667604086085,
            "time": "2025-05-08T07:56:00+00:00",
            "type": "high"
        },
        {
            "height": -0.33507140487196885,
            "time": "2025-05-08T14:02:00+00:00",
            "type": "low"
        },
        {
            "height": 0.4689722963518078,
            "time": "2025-05-08T19:56:00+00:00",
            "type": "high"
        },
        {
            "height": -0.4659897869658058,
            "time": "2025-05-09T02:06:00+00:00",
            "type": "low"
        },
        {
            "height": 0.6230510670984798,
            "time": "2025-05-09T08:30:00+00:00",
            "type": "high"
        },
        {
            "height": -0.38959188851775917,
            "time": "2025-05-09T14:46:00+00:00",
            "type": "low"
        },
        {
            "height": 0.44850355726375113,
            "time": "2025-05-09T20:36:00+00:00",
            "type": "high"
        },
        {
            "height": -0.4695497341698729,
            "time": "2025-05-10T02:37:00+00:00",
            "type": "low"
        },
        {
            "height": 0.6956169299019338,
            "time": "2025-05-10T09:03:00+00:00",
            "type": "high"
        },
        {
            "height": -0.4373028401820823,
            "time": "2025-05-10T15:26:00+00:00",
            "type": "low"
        },
        {
            "height": 0.42498281907070756,
            "time": "2025-05-10T21:15:00+00:00",
            "type": "high"
        },
        {
            "height": -0.46311288028062,
            "time": "2025-05-11T03:07:00+00:00",
            "type": "low"
        },
        {
            "height": 0.7493360854070256,
            "time": "2025-05-11T09:36:00+00:00",
            "type": "high"
        },
        {
            "height": -0.4737133757819217,
            "time": "2025-05-11T16:05:00+00:00",
            "type": "low"
        },
        {
            "height": 0.39811737100590794,
            "time": "2025-05-11T21:54:00+00:00",
            "type": "high"
        },
        {
            "height": -0.4457696075049704,
            "time": "2025-05-12T03:37:00+00:00",
            "type": "low"
        },
        {
            "height": 0.7820889326142894,
            "time": "2025-05-12T10:08:00+00:00",
            "type": "high"
        },
        {
            "height": -0.4956973629233716,
            "time": "2025-05-12T16:42:00+00:00",
            "type": "low"
        },
        {
            "height": 0.36858641499198785,
            "time": "2025-05-12T22:33:00+00:00",
            "type": "high"
        },
        {
            "height": -0.41902501989693486,
            "time": "2025-05-13T04:08:00+00:00",
            "type": "low"
        },
        {
            "height": 0.7946021263305242,
            "time": "2025-05-13T10:42:00+00:00",
            "type": "high"
        },
        {
            "height": -0.5023340759489447,
            "time": "2025-05-13T17:21:00+00:00",
            "type": "low"
        },
        {
            "height": 0.3372084088373909,
            "time": "2025-05-13T23:12:00+00:00",
            "type": "high"
        },
        {
            "height": -0.38556565941138266,
            "time": "2025-05-14T04:41:00+00:00",
            "type": "low"
        },
        {
            "height": 0.7896827846136897,
            "time": "2025-05-14T11:17:00+00:00",
            "type": "high"
        },
        {
            "height": -0.4953007097574054,
            "time": "2025-05-14T18:02:00+00:00",
            "type": "low"
        },
        {
            "height": 0.30487198311570374,
            "time": "2025-05-14T23:53:00+00:00",
            "type": "high"
        },
        {
            "height": -0.3482738742910315,
            "time": "2025-05-15T05:16:00+00:00",
            "type": "low"
        },
        {
            "height": 0.7715081330532819,
            "time": "2025-05-15T11:54:00+00:00",
            "type": "high"
        },
        {
            "height": -0.478783543100611,
            "time": "2025-05-15T18:46:00+00:00",
            "type": "low"
        },
        {
            "height": 0.27340346598390586,
            "time": "2025-05-16T00:37:00+00:00",
            "type": "high"
        },
        {
            "height": -0.30982374112581235,
            "time": "2025-05-16T05:55:00+00:00",
            "type": "low"
        },
        {
            "height": 0.7449659771034064,
            "time": "2025-05-16T12:36:00+00:00",
            "type": "high"
        },
        {
            "height": -0.4591830485651376,
            "time": "2025-05-16T19:33:00+00:00",
            "type": "low"
        }
    ],
    "meta": {
        "cost": 1,
        "dailyQuota": 10,
        "datum": "MSL",
        "end": "2025-05-17 00:00",
        "lat": -33.8908,
        "lng": 151.2773,
        "offset": 0,
        "requestCount": 3,
        "start": "2025-05-07 00:00",
        "station": {
            "distance": 6,
            "lat": -33.85,
            "lng": 151.233,
            "name": "fort denison",
            "source": "uhslc"
        }
    },
    "last_updated": "2025-05-07 17:13:59"
}