{
    "hours": [
        {
            "swellDirection": {
                "sg": 114.92
            },
            "swellHeight": {
                "sg": 2.1
            },
            "swellPeriod": {
                "sg": 8.04
            },
            "time": "2026-01-21T00:00:00+00:00"
        },
        {
            "swellDirection": {
                "sg": 115.32
            },
            "swellHeight": {
                "sg": 2.1
            },
            "swellPeriod": {
                "sg": 8.06
            },
            "time": "2026-01-21T01:00:00+00:00"
        },
        {
            "swellDirection": {
                "sg": 115.73
            },
            "swellHeight": {
                "sg": 2.09
            },
            "swellPeriod": {
                "sg": 8.07
            },
            "time": "2026-01-21T02:00:00+00:00"
        },
        {
            "swellDirection": {
                "sg": 116.13
            },
            "swellHeight": {
                "sg": 2.09
            },
            "swellPeriod": {
                "sg": 8.09
            },
            "time": "2026-01-21T03:00:00+00:00"
        },
        {
            "swellDirection": {
                "sg": 116.19
            },
            "swellHeight": {
                "sg": 2.1
            },
            "swellPeriod": {
                "sg": 8.14
            },
            "time": "2026-01-21T04:00:00+00:00"
        },
        {
            "swellDirection": {
                "sg": 116.25
            },
            "swellHeight": {
                "sg": 2.1
            },
            "swellPeriod": {
                "sg": 8.19
            },
            "time": "2026-01-21T05:00:00+00:00"
        },
        {
            "swellDirection": {
                "sg": 116.31
            },
            "swellHeight": {
                "sg": 2.11
            },
            "swellPeriod": {
                "sg": 8.24
            },
            "time": "2026-01-21T06:00:00+00:00"
        },
        {
            "swellDirection": {
                "sg": 116.64
            },
            "swellHeight": {
                "sg": 2.12
            },
            "swellPeriod": {
                "sg": 8.26
            },
            "time": "2026-01-21T07:00:00+00:00"
        },
        {
            "swellDirection": {
                "sg": 116.98
            },
            "swellHeight": {
                "sg": 2.12
            },
            "swellPeriod": {
                "sg": 8.27
            },
            "time": "2026-01-21T08:00:00+00:00"
        },
        {
            "swellDirection": {
                "sg": 117.31
            },
            "swellHeight": {
                "sg": 2.13
            },
            "swellPeriod": {
                "sg": 8.29
            },
            "time": "2026-01-21T09:00:00+00:00"
        },
        {
            "swellDirection": {
                "sg": 117.56
            },
            "swellHeight": {
                "sg": 2.12
            },
            "swellPeriod": {
                "sg": 8.3
            },
            "time": "2026-01-21T10:00:00+00:00"
        },
        {
            "swellDirection": {
                "sg": 117.8
            },
            "swellHeight": {
                "sg": 2.12
            },
            "swellPeriod": {
                "sg": 8.3
            },
            "time": "2026-01-21T11:00:00+00:00"
        },
        {
            "swellDirection": {
                "sg": 118.05
            },
            "swellHeight": {
                "sg": 2.11
            },
            "swellPeriod": {
                "sg": 8.31
            },
            "time": "2026-01-21T12:00:00+00:00"
        },
        {
            "swellDirection": {
                "sg": 118.14
            },
            "swellHeight": {
                "sg": 2.09
            },
            "swellPeriod": {
                "sg": 8.32
            },
            "time": "2026-01-21T13:00:00+00:00"
        },
        {
            "swellDirection": {
                "sg": 118.24
            },
            "swellHeight": {
                "sg": 2.07
            },
            "swellPeriod": {
                "sg": 8.33
            },
            "time": "2026-01-21T14:00:00+00:00"
        },
        {
            "swellDirection": {
                "sg": 118.33
            },
            "swellHeight": {
                "sg": 2.05
            },
            "swellPeriod": {
                "sg": 8.34
            },
            "time": "2026-01-21T15:00:00+00:00"
        },
        {
            "swellDirection": {
                "sg": 118.4
            },
            "swellHeight": {
                "sg": 2.03
            },
            "swellPeriod": {
                "sg": 8.33
            },
            "time": "2026-01-21T16:00:00+00:00"
        },
        {
            "swellDirection": {
                "sg": 118.48
            },
            "swellHeight": {
                "sg": 2.0
            },
            "swellPeriod": {
                "sg": 8.31
            },
            "time": "2026-01-21T17:00:00+00:00"
        },
        {
            "swellDirection": {
                "sg": 118.55
            },
            "swellHeight": {
                "sg": 1.98
            },
            "swellPeriod": {
                "sg": 8.3
            },
            "time": "2026-01-21T18:00:00+00:00"
        },
        {
            "swellDirection": {
                "sg": 118.71
            },
            "swellHeight": {
                "sg": 1.95
            },
            "swellPeriod": {
                "sg": 8.27
            },
            "time": "2026-01-21T19:00:00+00:00"
        },
        {
            "swellDirection": {
                "sg": 118.88
            },
            "swellHeight": {
                "sg": 1.91
            },
            "swellPeriod": {
                "sg": 8.24
            },
            "time": "2026-01-21T20:00:00+00:00"
        },
        {
            "swellDirection": {
                "sg": 119.04
            },
            "swellHeight": {
                "sg": 1.88
            },
            "swellPeriod": {
                "sg": 8.21
            },
            "time": "2026-01-21T21:00:00+00:00"
        },
        {
            "swellDirection": {
                "sg": 118.91
            },
            "swellHeight": {
                "sg": 1.84
            },
            "swellPeriod": {
                "sg": 8.22
            },
            "time": "2026-01-21T22:00:00+00:00"
        },
        {
            "swellDirection": {
                "sg": 118.79
            },
            "swellHeight": {
                "sg": 1.79
            },
            "swellPeriod": {
                "sg": 8.22
            },
            "time": "2026-01-21T23:00:00+00:00"
        },
        {
            "swellDirection": {
                "sg": 118.66
            },
            "swellHeight": {
                "sg": 1.75
            },
            "swellPeriod": {
                "sg": 8.23
            },
            "time": "2026-01-22T00:00:00+00:00"
        },
        {
            "swellDirection": {
                "sg": 115.9
            },
            "swellHeight": {
                "sg": 1.65
            },
            "swellPeriod": {
                "sg": 8.38
            },
            "time": "2026-01-22T01:00:00+00:00"
        },
        {
            "swellDirection": {
                "sg": 113.14
            },
            "swellHeight": {
                "sg": 1.55
            },
            "swellPeriod": {
                "sg": 8.52
            },
            "time": "2026-01-22T02:00:00+00:00"
        },
        {
            "swellDirection": {
                "sg": 110.38
            },
            "swellHeight": {
                "sg": 1.45
            },
            "swellPeriod": {
                "sg": 8.67
            },
            "time": "2026-01-22T03:00:00+00:00"
        },
        {
            "swellDirection": {
                "sg": 110.59
            },
            "swellHeight": {
                "sg": 1.42
            },
            "swellPeriod": {
                "sg": 8.68
            },
            "time": "2026-01-22T04:00:00+00:00"
        },
        {
            "swellDirection": {
                "sg": 110.81
            },
            "swellHeight": {
                "sg": 1.4
            },
            "swellPeriod": {
                "sg": 8.69
            },
            "time": "2026-01-22T05:00:00+00:00"
        },
        {
            "swellDirection": {
                "sg": 111.02
            },
            "swellHeight": {
                "sg": 1.37
            },
            "swellPeriod": {
                "sg": 8.7
            },
            "time": "2026-01-22T06:00:00+00:00"
        },
        {
            "swellDirection": {
                "sg": 114.79
            },
            "swellHeight": {
                "sg": 1.31
            },
            "swellPeriod": {
                "sg": 8.26
            },
            "time": "2026-01-22T07:00:00+00:00"
        },
        {
            "swellDirection": {
                "sg": 118.57
            },
            "swellHeight": {
                "sg": 1.25
            },
            "swellPeriod": {
                "sg": 7.81
            },
            "time": "2026-01-22T08:00:00+00:00"
        },
        {
            "swellDirection": {
                "sg": 122.34
            },
            "swellHeight": {
                "sg": 1.19
            },
            "swellPeriod": {
                "sg": 7.37
            },
            "time": "2026-01-22T09:00:00+00:00"
        },
        {
            "swellDirection": {
                "sg": 135.13
            },
            "swellHeight": {
                "sg": 1.32
            },
            "swellPeriod": {
                "sg": 7.62
            },
            "time": "2026-01-22T10:00:00+00:00"
        },
        {
            "swellDirection": {
                "sg": 147.91
            },
            "swellHeight": {
                "sg": 1.45
            },
            "swellPeriod": {
                "sg": 7.87
            },
            "time": "2026-01-22T11:00:00+00:00"
        },
        {
            "swellDirection": {
                "sg": 160.7
            },
            "swellHeight": {
                "sg": 1.58
            },
            "swellPeriod": {
                "sg": 8.12
            },
            "time": "2026-01-22T12:00:00+00:00"
        },
        {
            "swellDirection": {
                "sg": 163.92
            },
            "swellHeight": {
                "sg": 1.89
            },
            "swellPeriod": {
                "sg": 7.83
            },
            "time": "2026-01-22T13:00:00+00:00"
        },
        {
            "swellDirection": {
                "sg": 167.13
            },
            "swellHeight": {
                "sg": 2.2
            },
            "swellPeriod": {
                "sg": 7.55
            },
            "time": "2026-01-22T14:00:00+00:00"
        },
        {
            "swellDirection": {
                "sg": 170.35
            },
            "swellHeight": {
                "sg": 2.51
            },
            "swellPeriod": {
                "sg": 7.26
            },
            "time": "2026-01-22T15:00:00+00:00"
        },
        {
            "swellDirection": {
                "sg": 171.23
            },
            "swellHeight": {
                "sg": 2.52
            },
            "swellPeriod": {
                "sg": 7.32
            },
            "time": "2026-01-22T16:00:00+00:00"
        },
        {
            "swellDirection": {
                "sg": 172.12
            },
            "swellHeight": {
                "sg": 2.54
            },
            "swellPeriod": {
                "sg": 7.39
            },
            "time": "2026-01-22T17:00:00+00:00"
        },
        {
            "swellDirection": {
                "sg": 173.0
            },
            "swellHeight": {
                "sg": 2.55
            },
            "swellPeriod": {
                "sg": 7.45
            },
            "time": "2026-01-22T18:00:00+00:00"
        },
        {
            "swellDirection": {
                "sg": 172.15
            },
            "swellHeight": {
                "sg": 2.55
            },
            "swellPeriod": {
                "sg": 7.57
            },
            "time": "2026-01-22T19:00:00+00:00"
        },
        {
            "swellDirection": {
                "sg": 171.31
            },
            "swellHeight": {
                "sg": 2.56
            },
            "swellPeriod": {
                "sg": 7.69
            },
            "time": "2026-01-22T20:00:00+00:00"
        },
        {
            "swellDirection": {
                "sg": 170.46
            },
            "swellHeight": {
                "sg": 2.56
            },
            "swellPeriod": {
                "sg": 7.81
            },
            "time": "2026-01-22T21:00:00+00:00"
        },
        {
            "swellDirection": {
                "sg": 166.82
            },
            "swellHeight": {
                "sg": 2.59
            },
            "swellPeriod": {
                "sg": 7.79
            },
            "time": "2026-01-22T22:00:00+00:00"
        },
        {
            "swellDirection": {
                "sg": 163.17
            },
            "swellHeight": {
                "sg": 2.62
            },
            "swellPeriod": {
                "sg": 7.76
            },
            "time": "2026-01-22T23:00:00+00:00"
        },
        {
            "swellDirection": {
                "sg": 159.53
            },
            "swellHeight": {
                "sg": 2.65
            },
            "swellPeriod": {
                "sg": 7.74
            },
            "time": "2026-01-23T00:00:00+00:00"
        },
        {
            "swellDirection": {
                "sg": 158.73
            },
            "swellHeight": {
                "sg": 2.57
            },
            "swellPeriod": {
                "sg": 7.71
            },
            "time": "2026-01-23T01:00:00+00:00"
        },
        {
            "swellDirection": {
                "sg": 157.92
            },
            "swellHeight": {
                "sg": 2.5
            },
            "swellPeriod": {
                "sg": 7.69
            },
            "time": "2026-01-23T02:00:00+00:00"
        },
        {
            "swellDirection": {
                "sg": 157.12
            },
            "swellHeight": {
                "sg": 2.42
            },
            "swellPeriod": {
                "sg": 7.66
            },
            "time": "2026-01-23T03:00:00+00:00"
        },
        {
            "swellDirection": {
                "sg": 156.16
            },
            "swellHeight": {
                "sg": 2.36
            },
            "swellPeriod": {
                "sg": 7.64
            },
            "time": "2026-01-23T04:00:00+00:00"
        },
        {
            "swellDirection": {
                "sg": 155.19
            },
            "swellHeight": {
                "sg": 2.31
            },
            "swellPeriod": {
                "sg": 7.62
            },
            "time": "2026-01-23T05:00:00+00:00"
        },
        {
            "swellDirection": {
                "sg": 154.23
            },
            "swellHeight": {
                "sg": 2.25
            },
            "swellPeriod": {
                "sg": 7.6
            },
            "time": "2026-01-23T06:00:00+00:00"
        },
        {
            "swellDirection": {
                "sg": 153.72
            },
            "swellHeight": {
                "sg": 2.2
            },
            "swellPeriod": {
                "sg": 7.59
            },
            "time": "2026-01-23T07:00:00+00:00"
        },
        {
            "swellDirection": {
                "sg": 153.21
            },
            "swellHeight": {
                "sg": 2.15
            },
            "swellPeriod": {
                "sg": 7.57
            },
            "time": "2026-01-23T08:00:00+00:00"
        },
        {
            "swellDirection": {
                "sg": 152.7
            },
            "swellHeight": {
                "sg": 2.1
            },
            "swellPeriod": {
                "sg": 7.56
            },
            "time": "2026-01-23T09:00:00+00:00"
        },
        {
            "swellDirection": {
                "sg": 152.0
            },
            "swellHeight": {
                "sg": 2.07
            },
            "swellPeriod": {
                "sg": 7.52
            },
            "time": "2026-01-23T10:00:00+00:00"
        },
        {
            "swellDirection": {
                "sg": 151.31
            },
            "swellHeight": {
                "sg": 2.03
            },
            "swellPeriod": {
                "sg": 7.48
            },
            "time": "2026-01-23T11:00:00+00:00"
        },
        {
            "swellDirection": {
                "sg": 150.61
            },
            "swellHeight": {
                "sg": 2.0
            },
            "swellPeriod": {
                "sg": 7.44
            },
            "time": "2026-01-23T12:00:00+00:00"
        },
        {
            "swellDirection": {
                "sg": 150.13
            },
            "swellHeight": {
                "sg": 1.97
            },
            "swellPeriod": {
                "sg": 7.42
            },
            "time": "2026-01-23T13:00:00+00:00"
        },
        {
            "swellDirection": {
                "sg": 149.64
            },
            "swellHeight": {
                "sg": 1.93
            },
            "swellPeriod": {
                "sg": 7.4
            },
            "time": "2026-01-23T14:00:00+00:00"
        },
        {
            "swellDirection": {
                "sg": 149.16
            },
            "swellHeight": {
                "sg": 1.9
            },
            "swellPeriod": {
                "sg": 7.38
            },
            "time": "2026-01-23T15:00:00+00:00"
        },
        {
            "swellDirection": {
                "sg": 148.75
            },
            "swellHeight": {
                "sg": 1.87
            },
            "swellPeriod": {
                "sg": 7.36
            },
            "time": "2026-01-23T16:00:00+00:00"
        },
        {
            "swellDirection": {
                "sg": 148.33
            },
            "swellHeight": {
                "sg": 1.85
            },
            "swellPeriod": {
                "sg": 7.34
            },
            "time": "2026-01-23T17:00:00+00:00"
        },
        {
            "swellDirection": {
                "sg": 147.92
            },
            "swellHeight": {
                "sg": 1.82
            },
            "swellPeriod": {
                "sg": 7.32
            },
            "time": "2026-01-23T18:00:00+00:00"
        },
        {
            "swellDirection": {
                "sg": 147.62
            },
            "swellHeight": {
                "sg": 1.79
            },
            "swellPeriod": {
                "sg": 7.3
            },
            "time": "2026-01-23T19:00:00+00:00"
        },
        {
            "swellDirection": {
                "sg": 147.33
            },
            "swellHeight": {
                "sg": 1.77
            },
            "swellPeriod": {
                "sg": 7.29
            },
            "time": "2026-01-23T20:00:00+00:00"
        },
        {
            "swellDirection": {
                "sg": 147.03
            },
            "swellHeight": {
                "sg": 1.74
            },
            "swellPeriod": {
                "sg": 7.27
            },
            "time": "2026-01-23T21:00:00+00:00"
        },
        {
            "swellDirection": {
                "sg": 146.75
            },
            "swellHeight": {
                "sg": 1.72
            },
            "swellPeriod": {
                "sg": 7.26
            },
            "time": "2026-01-23T22:00:00+00:00"
        },
        {
            "swellDirection": {
                "sg": 146.48
            },
            "swellHeight": {
                "sg": 1.69
            },
            "swellPeriod": {
                "sg": 7.24
            },
            "time": "2026-01-23T23:00:00+00:00"
        },
        {
            "swellDirection": {
                "sg": 146.2
            },
            "swellHeight": {
                "sg": 1.67
            },
            "swellPeriod": {
                "sg": 7.23
            },
            "time": "2026-01-24T00:00:00+00:00"
        },
        {
            "swellDirection": {
                "sg": 141.43
            },
            "swellHeight": {
                "sg": 1.56
            },
            "swellPeriod": {
                "sg": 7.22
            },
            "time": "2026-01-24T01:00:00+00:00"
        },
        {
            "swellDirection": {
                "sg": 136.67
            },
            "swellHeight": {
                "sg": 1.44
            },
            "swellPeriod": {
                "sg": 7.22
            },
            "time": "2026-01-24T02:00:00+00:00"
        },
        {
            "swellDirection": {
                "sg": 131.9
            },
            "swellHeight": {
                "sg": 1.33
            },
            "swellPeriod": {
                "sg": 7.21
            },
            "time": "2026-01-24T03:00:00+00:00"
        },
        {
            "swellDirection": {
                "sg": 134.35
            },
            "swellHeight": {
                "sg": 1.27
            },
            "swellPeriod": {
                "sg": 7.28
            },
            "time": "2026-01-24T04:00:00+00:00"
        },
        {
            "swellDirection": {
                "sg": 136.81
            },
            "swellHeight": {
                "sg": 1.22
            },
            "swellPeriod": {
                "sg": 7.34
            },
            "time": "2026-01-24T05:00:00+00:00"
        },
        {
            "swellDirection": {
                "sg": 139.26
            },
            "swellHeight": {
                "sg": 1.16
            },
            "swellPeriod": {
                "sg": 7.41
            },
            "time": "2026-01-24T06:00:00+00:00"
        },
        {
            "swellDirection": {
                "sg": 138.3
            },
            "swellHeight": {
                "sg": 1.19
            },
            "swellPeriod": {
                "sg": 7.59
            },
            "time": "2026-01-24T07:00:00+00:00"
        },
        {
            "swellDirection": {
                "sg": 137.33
            },
            "swellHeight": {
                "sg": 1.23
            },
            "swellPeriod": {
                "sg": 7.78
            },
            "time": "2026-01-24T08:00:00+00:00"
        },
        {
            "swellDirection": {
                "sg": 136.37
            },
            "swellHeight": {
                "sg": 1.26
            },
            "swellPeriod": {
                "sg": 7.96
            },
            "time": "2026-01-24T09:00:00+00:00"
        },
        {
            "swellDirection": {
                "sg": 139.3
            },
            "swellHeight": {
                "sg": 1.32
            },
            "swellPeriod": {
                "sg": 7.97
            },
            "time": "2026-01-24T10:00:00+00:00"
        },
        {
            "swellDirection": {
                "sg": 142.22
            },
            "swellHeight": {
                "sg": 1.39
            },
            "swellPeriod": {
                "sg": 7.98
            },
            "time": "2026-01-24T11:00:00+00:00"
        },
        {
            "swellDirection": {
                "sg": 145.15
            },
            "swellHeight": {
                "sg": 1.45
            },
            "swellPeriod": {
                "sg": 7.99
            },
            "time": "2026-01-24T12:00:00+00:00"
        },
        {
            "swellDirection": {
                "sg": 144.4
            },
            "swellHeight": {
                "sg": 1.48
            },
            "swellPeriod": {
                "sg": 7.99
            },
            "time": "2026-01-24T13:00:00+00:00"
        },
        {
            "swellDirection": {
                "sg": 143.66
            },
            "swellHeight": {
                "sg": 1.5
            },
            "swellPeriod": {
                "sg": 8.0
            },
            "time": "2026-01-24T14:00:00+00:00"
        },
        {
            "swellDirection": {
                "sg": 142.91
            },
            "swellHeight": {
                "sg": 1.53
            },
            "swellPeriod": {
                "sg": 8.0
            },
            "time": "2026-01-24T15:00:00+00:00"
        },
        {
            "swellDirection": {
                "sg": 142.93
            },
            "swellHeight": {
                "sg": 1.55
            },
            "swellPeriod": {
                "sg": 8.1
            },
            "time": "2026-01-24T16:00:00+00:00"
        },
        {
            "swellDirection": {
                "sg": 142.96
            },
            "swellHeight": {
                "sg": 1.56
            },
            "swellPeriod": {
                "sg": 8.2
            },
            "time": "2026-01-24T17:00:00+00:00"
        },
        {
            "swellDirection": {
                "sg": 142.98
            },
            "swellHeight": {
                "sg": 1.58
            },
            "swellPeriod": {
                "sg": 8.3
            },
            "time": "2026-01-24T18:00:00+00:00"
        },
        {
            "swellDirection": {
                "sg": 142.93
            },
            "swellHeight": {
                "sg": 1.6
            },
            "swellPeriod": {
                "sg": 8.37
            },
            "time": "2026-01-24T19:00:00+00:00"
        },
        {
            "swellDirection": {
                "sg": 142.88
            },
            "swellHeight": {
                "sg": 1.61
            },
            "swellPeriod": {
                "sg": 8.44
            },
            "time": "2026-01-24T20:00:00+00:00"
        },
        {
            "swellDirection": {
                "sg": 142.83
            },
            "swellHeight": {
                "sg": 1.63
            },
            "swellPeriod": {
                "sg": 8.51
            },
            "time": "2026-01-24T21:00:00+00:00"
        },
        {
            "swellDirection": {
                "sg": 142.69
            },
            "swellHeight": {
                "sg": 1.64
            },
            "swellPeriod": {
                "sg": 8.56
            },
            "time": "2026-01-24T22:00:00+00:00"
        },
        {
            "swellDirection": {
                "sg": 142.55
            },
            "swellHeight": {
                "sg": 1.66
            },
            "swellPeriod": {
                "sg": 8.61
            },
            "time": "2026-01-24T23:00:00+00:00"
        },
        {
            "swellDirection": {
                "sg": 142.41
            },
            "swellHeight": {
                "sg": 1.67
            },
            "swellPeriod": {
                "sg": 8.66
            },
            "time": "2026-01-25T00:00:00+00:00"
        },
        {
            "swellDirection": {
                "sg": 142.5
            },
            "swellHeight": {
                "sg": 1.67
            },
            "swellPeriod": {
                "sg": 8.74
            },
            "time": "2026-01-25T01:00:00+00:00"
        },
        {
            "swellDirection": {
                "sg": 142.58
            },
            "swellHeight": {
                "sg": 1.68
            },
            "swellPeriod": {
                "sg": 8.83
            },
            "time": "2026-01-25T02:00:00+00:00"
        },
        {
            "swellDirection": {
                "sg": 142.67
            },
            "swellHeight": {
                "sg": 1.68
            },
            "swellPeriod": {
                "sg": 8.91
            },
            "time": "2026-01-25T03:00:00+00:00"
        },
        {
            "swellDirection": {
                "sg": 142.68
            },
            "swellHeight": {
                "sg": 1.7
            },
            "swellPeriod": {
                "sg": 8.98
            },
            "time": "2026-01-25T04:00:00+00:00"
        },
        {
            "swellDirection": {
                "sg": 142.69
            },
            "swellHeight": {
                "sg": 1.71
            },
            "swellPeriod": {
                "sg": 9.06
            },
            "time": "2026-01-25T05:00:00+00:00"
        },
        {
            "swellDirection": {
                "sg": 142.7
            },
            "swellHeight": {
                "sg": 1.73
            },
            "swellPeriod": {
                "sg": 9.13
            },
            "time": "2026-01-25T06:00:00+00:00"
        },
        {
            "swellDirection": {
                "sg": 142.82
            },
            "swellHeight": {
                "sg": 1.75
            },
            "swellPeriod": {
                "sg": 9.22
            },
            "time": "2026-01-25T07:00:00+00:00"
        },
        {
            "swellDirection": {
                "sg": 142.95
            },
            "swellHeight": {
                "sg": 1.77
            },
            "swellPeriod": {
                "sg": 9.31
            },
            "time": "2026-01-25T08:00:00+00:00"
        },
        {
            "swellDirection": {
                "sg": 143.07
            },
            "swellHeight": {
                "sg": 1.79
            },
            "swellPeriod": {
                "sg": 9.4
            },
            "time": "2026-01-25T09:00:00+00:00"
        },
        {
            "swellDirection": {
                "sg": 142.61
            },
            "swellHeight": {
                "sg": 1.79
            },
            "swellPeriod": {
                "sg": 9.54
            },
            "time": "2026-01-25T10:00:00+00:00"
        },
        {
            "swellDirection": {
                "sg": 142.16
            },
            "swellHeight": {
                "sg": 1.79
            },
            "swellPeriod": {
                "sg": 9.69
            },
            "time": "2026-01-25T11:00:00+00:00"
        },
        {
            "swellDirection": {
                "sg": 141.7
            },
            "swellHeight": {
                "sg": 1.79
            },
            "swellPeriod": {
                "sg": 9.83
            },
            "time": "2026-01-25T12:00:00+00:00"
        },
        {
            "swellDirection": {
                "sg": 140.87
            },
            "swellHeight": {
                "sg": 1.76
            },
            "swellPeriod": {
                "sg": 9.95
            },
            "time": "2026-01-25T13:00:00+00:00"
        },
        {
            "swellDirection": {
                "sg": 140.03
            },
            "swellHeight": {
                "sg": 1.74
            },
            "swellPeriod": {
                "sg": 10.07
            },
            "time": "2026-01-25T14:00:00+00:00"
        },
        {
            "swellDirection": {
                "sg": 139.2
            },
            "swellHeight": {
                "sg": 1.71
            },
            "swellPeriod": {
                "sg": 10.19
            },
            "time": "2026-01-25T15:00:00+00:00"
        },
        {
            "swellDirection": {
                "sg": 140.41
            },
            "swellHeight": {
                "sg": 1.77
            },
            "swellPeriod": {
                "sg": 10.02
            },
            "time": "2026-01-25T16:00:00+00:00"
        },
        {
            "swellDirection": {
                "sg": 141.62
            },
            "swellHeight": {
                "sg": 1.84
            },
            "swellPeriod": {
                "sg": 9.84
            },
            "time": "2026-01-25T17:00:00+00:00"
        },
        {
            "swellDirection": {
                "sg": 142.83
            },
            "swellHeight": {
                "sg": 1.9
            },
            "swellPeriod": {
                "sg": 9.67
            },
            "time": "2026-01-25T18:00:00+00:00"
        },
        {
            "swellDirection": {
                "sg": 143.16
            },
            "swellHeight": {
                "sg": 1.94
            },
            "swellPeriod": {
                "sg": 9.48
            },
            "time": "2026-01-25T19:00:00+00:00"
        },
        {
            "swellDirection": {
                "sg": 143.48
            },
            "swellHeight": {
                "sg": 1.97
            },
            "swellPeriod": {
                "sg": 9.3
            },
            "time": "2026-01-25T20:00:00+00:00"
        },
        {
            "swellDirection": {
                "sg": 143.81
            },
            "swellHeight": {
                "sg": 2.01
            },
            "swellPeriod": {
                "sg": 9.11
            },
            "time": "2026-01-25T21:00:00+00:00"
        },
        {
            "swellDirection": {
                "sg": 144.5
            },
            "swellHeight": {
                "sg": 2.05
            },
            "swellPeriod": {
                "sg": 8.9
            },
            "time": "2026-01-25T22:00:00+00:00"
        },
        {
            "swellDirection": {
                "sg": 145.19
            },
            "swellHeight": {
                "sg": 2.09
            },
            "swellPeriod": {
                "sg": 8.68
            },
            "time": "2026-01-25T23:00:00+00:00"
        },
        {
            "swellDirection": {
                "sg": 145.88
            },
            "swellHeight": {
                "sg": 2.13
            },
            "swellPeriod": {
                "sg": 8.47
            },
            "time": "2026-01-26T00:00:00+00:00"
        },
        {
            "swellDirection": {
                "sg": 146.99
            },
            "swellHeight": {
                "sg": 2.17
            },
            "swellPeriod": {
                "sg": 8.36
            },
            "time": "2026-01-26T01:00:00+00:00"
        },
        {
            "swellDirection": {
                "sg": 148.1
            },
            "swellHeight": {
                "sg": 2.21
            },
            "swellPeriod": {
                "sg": 8.25
            },
            "time": "2026-01-26T02:00:00+00:00"
        },
        {
            "swellDirection": {
                "sg": 149.21
            },
            "swellHeight": {
                "sg": 2.25
            },
            "swellPeriod": {
                "sg": 8.14
            },
            "time": "2026-01-26T03:00:00+00:00"
        },
        {
            "swellDirection": {
                "sg": 149.81
            },
            "swellHeight": {
                "sg": 2.25
            },
            "swellPeriod": {
                "sg": 8.16
            },
            "time": "2026-01-26T04:00:00+00:00"
        },
        {
            "swellDirection": {
                "sg": 150.41
            },
            "swellHeight": {
                "sg": 2.25
            },
            "swellPeriod": {
                "sg": 8.17
            },
            "time": "2026-01-26T05:00:00+00:00"
        },
        {
            "swellDirection": {
                "sg": 151.01
            },
            "swellHeight": {
                "sg": 2.25
            },
            "swellPeriod": {
                "sg": 8.19
            },
            "time": "2026-01-26T06:00:00+00:00"
        },
        {
            "swellDirection": {
                "sg": 152.95
            },
            "swellHeight": {
                "sg": 2.27
            },
            "swellPeriod": {
                "sg": 8.08
            },
            "time": "2026-01-26T07:00:00+00:00"
        },
        {
            "swellDirection": {
                "sg": 154.88
            },
            "swellHeight": {
                "sg": 2.3
            },
            "swellPeriod": {
                "sg": 7.96
            },
            "time": "2026-01-26T08:00:00+00:00"
        },
        {
            "swellDirection": {
                "sg": 156.82
            },
            "swellHeight": {
                "sg": 2.32
            },
            "swellPeriod": {
                "sg": 7.85
            },
            "time": "2026-01-26T09:00:00+00:00"
        },
        {
            "swellDirection": {
                "sg": 156.92
            },
            "swellHeight": {
                "sg": 2.3
            },
            "swellPeriod": {
                "sg": 7.8
            },
            "time": "2026-01-26T10:00:00+00:00"
        },
        {
            "swellDirection": {
                "sg": 157.01
            },
            "swellHeight": {
                "sg": 2.28
            },
            "swellPeriod": {
                "sg": 7.74
            },
            "time": "2026-01-26T11:00:00+00:00"
        },
        {
            "swellDirection": {
                "sg": 157.11
            },
            "swellHeight": {
                "sg": 2.26
            },
            "swellPeriod": {
                "sg": 7.69
            },
            "time": "2026-01-26T12:00:00+00:00"
        },
        {
            "swellDirection": {
                "sg": 156.41
            },
            "swellHeight": {
                "sg": 2.24
            },
            "swellPeriod": {
                "sg": 7.69
            },
            "time": "2026-01-26T13:00:00+00:00"
        },
        {
            "swellDirection": {
                "sg": 155.7
            },
            "swellHeight": {
                "sg": 2.21
            },
            "swellPeriod": {
                "sg": 7.68
            },
            "time": "2026-01-26T14:00:00+00:00"
        },
        {
            "swellDirection": {
                "sg": 155.0
            },
            "swellHeight": {
                "sg": 2.19
            },
            "swellPeriod": {
                "sg": 7.68
            },
            "time": "2026-01-26T15:00:00+00:00"
        },
        {
            "swellDirection": {
                "sg": 155.04
            },
            "swellHeight": {
                "sg": 2.11
            },
            "swellPeriod": {
                "sg": 7.46
            },
            "time": "2026-01-26T16:00:00+00:00"
        },
        {
            "swellDirection": {
                "sg": 155.08
            },
            "swellHeight": {
                "sg": 2.02
            },
            "swellPeriod": {
                "sg": 7.23
            },
            "time": "2026-01-26T17:00:00+00:00"
        },
        {
            "swellDirection": {
                "sg": 155.12
            },
            "swellHeight": {
                "sg": 1.94
            },
            "swellPeriod": {
                "sg": 7.01
            },
            "time": "2026-01-26T18:00:00+00:00"
        },
        {
            "swellDirection": {
                "sg": 149.43
            },
            "swellHeight": {
                "sg": 1.82
            },
            "swellPeriod": {
                "sg": 7.49
            },
            "time": "2026-01-26T19:00:00+00:00"
        },
        {
            "swellDirection": {
                "sg": 143.74
            },
            "swellHeight": {
                "sg": 1.7
            },
            "swellPeriod": {
                "sg": 7.98
            },
            "time": "2026-01-26T20:00:00+00:00"
        },
        {
            "swellDirection": {
                "sg": 138.05
            },
            "swellHeight": {
                "sg": 1.58
            },
            "swellPeriod": {
                "sg": 8.46
            },
            "time": "2026-01-26T21:00:00+00:00"
        },
        {
            "swellDirection": {
                "sg": 139.47
            },
            "swellHeight": {
                "sg": 1.63
            },
            "swellPeriod": {
                "sg": 8.37
            },
            "time": "2026-01-26T22:00:00+00:00"
        },
        {
            "swellDirection": {
                "sg": 140.89
            },
            "swellHeight": {
                "sg": 1.69
            },
            "swellPeriod": {
                "sg": 8.28
            },
            "time": "2026-01-26T23:00:00+00:00"
        },
        {
            "swellDirection": {
                "sg": 142.31
            },
            "swellHeight": {
                "sg": 1.74
            },
            "swellPeriod": {
                "sg": 8.19
            },
            "time": "2026-01-27T00:00:00+00:00"
        },
        {
            "swellDirection": {
                "sg": 144.27
            },
            "swellHeight": {
                "sg": 1.8
            },
            "swellPeriod": {
                "sg": 8.08
            },
            "time": "2026-01-27T01:00:00+00:00"
        },
        {
            "swellDirection": {
                "sg": 146.24
            },
            "swellHeight": {
                "sg": 1.87
            },
            "swellPeriod": {
                "sg": 7.98
            },
            "time": "2026-01-27T02:00:00+00:00"
        },
        {
            "swellDirection": {
                "sg": 148.2
            },
            "swellHeight": {
                "sg": 1.93
            },
            "swellPeriod": {
                "sg": 7.87
            },
            "time": "2026-01-27T03:00:00+00:00"
        },
        {
            "swellDirection": {
                "sg": 147.72
            },
            "swellHeight": {
                "sg": 1.9
            },
            "swellPeriod": {
                "sg": 7.86
            },
            "time": "2026-01-27T04:00:00+00:00"
        },
        {
            "swellDirection": {
                "sg": 147.23
            },
            "swellHeight": {
                "sg": 1.87
            },
            "swellPeriod": {
                "sg": 7.84
            },
            "time": "2026-01-27T05:00:00+00:00"
        },
        {
            "swellDirection": {
                "sg": 146.75
            },
            "swellHeight": {
                "sg": 1.84
            },
            "swellPeriod": {
                "sg": 7.83
            },
            "time": "2026-01-27T06:00:00+00:00"
        },
        {
            "swellDirection": {
                "sg": 146.07
            },
            "swellHeight": {
                "sg": 1.8
            },
            "swellPeriod": {
                "sg": 7.79
            },
            "time": "2026-01-27T07:00:00+00:00"
        },
        {
            "swellDirection": {
                "sg": 145.38
            },
            "swellHeight": {
                "sg": 1.77
            },
            "swellPeriod": {
                "sg": 7.76
            },
            "time": "2026-01-27T08:00:00+00:00"
        },
        {
            "swellDirection": {
                "sg": 144.7
            },
            "swellHeight": {
                "sg": 1.73
            },
            "swellPeriod": {
                "sg": 7.72
            },
            "time": "2026-01-27T09:00:00+00:00"
        },
        {
            "swellDirection": {
                "sg": 144.7
            },
            "swellHeight": {
                "sg": 1.68
            },
            "swellPeriod": {
                "sg": 7.69
            },
            "time": "2026-01-27T10:00:00+00:00"
        },
        {
            "swellDirection": {
                "sg": 144.69
            },
            "swellHeight": {
                "sg": 1.63
            },
            "swellPeriod": {
                "sg": 7.67
            },
            "time": "2026-01-27T11:00:00+00:00"
        },
        {
            "swellDirection": {
                "sg": 144.69
            },
            "swellHeight": {
                "sg": 1.58
            },
            "swellPeriod": {
                "sg": 7.64
            },
            "time": "2026-01-27T12:00:00+00:00"
        },
        {
            "swellDirection": {
                "sg": 146.62
            },
            "swellHeight": {
                "sg": 1.5
            },
            "swellPeriod": {
                "sg": 7.78
            },
            "time": "2026-01-27T13:00:00+00:00"
        },
        {
            "swellDirection": {
                "sg": 148.56
            },
            "swellHeight": {
                "sg": 1.42
            },
            "swellPeriod": {
                "sg": 7.91
            },
            "time": "2026-01-27T14:00:00+00:00"
        },
        {
            "swellDirection": {
                "sg": 150.49
            },
            "swellHeight": {
                "sg": 1.34
            },
            "swellPeriod": {
                "sg": 8.05
            },
            "time": "2026-01-27T15:00:00+00:00"
        },
        {
            "swellDirection": {
                "sg": 150.43
            },
            "swellHeight": {
                "sg": 1.3
            },
            "swellPeriod": {
                "sg": 8.04
            },
            "time": "2026-01-27T16:00:00+00:00"
        },
        {
            "swellDirection": {
                "sg": 150.37
            },
            "swellHeight": {
                "sg": 1.27
            },
            "swellPeriod": {
                "sg": 8.02
            },
            "time": "2026-01-27T17:00:00+00:00"
        },
        {
            "swellDirection": {
                "sg": 150.31
            },
            "swellHeight": {
                "sg": 1.23
            },
            "swellPeriod": {
                "sg": 8.01
            },
            "time": "2026-01-27T18:00:00+00:00"
        },
        {
            "swellDirection": {
                "sg": 150.35
            },
            "swellHeight": {
                "sg": 1.19
            },
            "swellPeriod": {
                "sg": 8.0
            },
            "time": "2026-01-27T19:00:00+00:00"
        },
        {
            "swellDirection": {
                "sg": 150.4
            },
            "swellHeight": {
                "sg": 1.16
            },
            "swellPeriod": {
                "sg": 8.0
            },
            "time": "2026-01-27T20:00:00+00:00"
        },
        {
            "swellDirection": {
                "sg": 150.44
            },
            "swellHeight": {
                "sg": 1.12
            },
            "swellPeriod": {
                "sg": 7.99
            },
            "time": "2026-01-27T21:00:00+00:00"
        },
        {
            "swellDirection": {
                "sg": 150.74
            },
            "swellHeight": {
                "sg": 1.08
            },
            "swellPeriod": {
                "sg": 8.01
            },
            "time": "2026-01-27T22:00:00+00:00"
        },
        {
            "swellDirection": {
                "sg": 151.03
            },
            "swellHeight": {
                "sg": 1.05
            },
            "swellPeriod": {
                "sg": 8.04
            },
            "time": "2026-01-27T23:00:00+00:00"
        },
        {
            "swellDirection": {
                "sg": 151.33
            },
            "swellHeight": {
                "sg": 1.01
            },
            "swellPeriod": {
                "sg": 8.06
            },
            "time": "2026-01-28T00:00:00+00:00"
        },
        {
            "swellDirection": {
                "sg": 151.21
            },
            "swellHeight": {
                "sg": 0.98
            },
            "swellPeriod": {
                "sg": 8.05
            },
            "time": "2026-01-28T01:00:00+00:00"
        },
        {
            "swellDirection": {
                "sg": 151.09
            },
            "swellHeight": {
                "sg": 0.94
            },
            "swellPeriod": {
                "sg": 8.05
            },
            "time": "2026-01-28T02:00:00+00:00"
        },
        {
            "swellDirection": {
                "sg": 150.97
            },
            "swellHeight": {
                "sg": 0.91
            },
            "swellPeriod": {
                "sg": 8.04
            },
            "time": "2026-01-28T03:00:00+00:00"
        },
        {
            "swellDirection": {
                "sg": 150.76
            },
            "swellHeight": {
                "sg": 0.88
            },
            "swellPeriod": {
                "sg": 8.05
            },
            "time": "2026-01-28T04:00:00+00:00"
        },
        {
            "swellDirection": {
                "sg": 150.54
            },
            "swellHeight": {
                "sg": 0.85
            },
            "swellPeriod": {
                "sg": 8.05
            },
            "time": "2026-01-28T05:00:00+00:00"
        },
        {
            "swellDirection": {
                "sg": 150.33
            },
            "swellHeight": {
                "sg": 0.82
            },
            "swellPeriod": {
                "sg": 8.06
            },
            "time": "2026-01-28T06:00:00+00:00"
        },
        {
            "swellDirection": {
                "sg": 150.06
            },
            "swellHeight": {
                "sg": 0.79
            },
            "swellPeriod": {
                "sg": 8.07
            },
            "time": "2026-01-28T07:00:00+00:00"
        },
        {
            "swellDirection": {
                "sg": 149.78
            },
            "swellHeight": {
                "sg": 0.77
            },
            "swellPeriod": {
                "sg": 8.09
            },
            "time": "2026-01-28T08:00:00+00:00"
        },
        {
            "swellDirection": {
                "sg": 149.51
            },
            "swellHeight": {
                "sg": 0.74
            },
            "swellPeriod": {
                "sg": 8.1
            },
            "time": "2026-01-28T09:00:00+00:00"
        },
        {
            "swellDirection": {
                "sg": 128.28
            },
            "swellHeight": {
                "sg": 0.75
            },
            "swellPeriod": {
                "sg": 7.17
            },
            "time": "2026-01-28T10:00:00+00:00"
        },
        {
            "swellDirection": {
                "sg": 107.06
            },
            "swellHeight": {
                "sg": 0.77
            },
            "swellPeriod": {
                "sg": 6.24
            },
            "time": "2026-01-28T11:00:00+00:00"
        },
        {
            "swellDirection": {
                "sg": 85.83
            },
            "swellHeight": {
                "sg": 0.78
            },
            "swellPeriod": {
                "sg": 5.31
            },
            "time": "2026-01-28T12:00:00+00:00"
        },
        {
            "swellDirection": {
                "sg": 76.65
            },
            "swellHeight": {
                "sg": 0.94
            },
            "swellPeriod": {
                "sg": 5.17
            },
            "time": "2026-01-28T13:00:00+00:00"
        },
        {
            "swellDirection": {
                "sg": 67.48
            },
            "swellHeight": {
                "sg": 1.09
            },
            "swellPeriod": {
                "sg": 5.02
            },
            "time": "2026-01-28T14:00:00+00:00"
        },
        {
            "swellDirection": {
                "sg": 58.3
            },
            "swellHeight": {
                "sg": 1.25
            },
            "swellPeriod": {
                "sg": 4.88
            },
            "time": "2026-01-28T15:00:00+00:00"
        },
        {
            "swellDirection": {
                "sg": 57.17
            },
            "swellHeight": {
                "sg": 1.24
            },
            "swellPeriod": {
                "sg": 4.82
            },
            "time": "2026-01-28T16:00:00+00:00"
        },
        {
            "swellDirection": {
                "sg": 56.04
            },
            "swellHeight": {
                "sg": 1.23
            },
            "swellPeriod": {
                "sg": 4.76
            },
            "time": "2026-01-28T17:00:00+00:00"
        },
        {
            "swellDirection": {
                "sg": 54.91
            },
            "swellHeight": {
                "sg": 1.22
            },
            "swellPeriod": {
                "sg": 4.7
            },
            "time": "2026-01-28T18:00:00+00:00"
        },
        {
            "swellDirection": {
                "sg": 55.22
            },
            "swellHeight": {
                "sg": 1.18
            },
            "swellPeriod": {
                "sg": 4.71
            },
            "time": "2026-01-28T19:00:00+00:00"
        },
        {
            "swellDirection": {
                "sg": 55.52
            },
            "swellHeight": {
                "sg": 1.14
            },
            "swellPeriod": {
                "sg": 4.72
            },
            "time": "2026-01-28T20:00:00+00:00"
        },
        {
            "swellDirection": {
                "sg": 55.83
            },
            "swellHeight": {
                "sg": 1.1
            },
            "swellPeriod": {
                "sg": 4.73
            },
            "time": "2026-01-28T21:00:00+00:00"
        },
        {
            "swellDirection": {
                "sg": 56.15
            },
            "swellHeight": {
                "sg": 1.04
            },
            "swellPeriod": {
                "sg": 4.79
            },
            "time": "2026-01-28T22:00:00+00:00"
        },
        {
            "swellDirection": {
                "sg": 56.46
            },
            "swellHeight": {
                "sg": 0.99
            },
            "swellPeriod": {
                "sg": 4.84
            },
            "time": "2026-01-28T23:00:00+00:00"
        },
        {
            "swellDirection": {
                "sg": 56.78
            },
            "swellHeight": {
                "sg": 0.93
            },
            "swellPeriod": {
                "sg": 4.9
            },
            "time": "2026-01-29T00:00:00+00:00"
        },
        {
            "swellDirection": {
                "sg": 57.42
            },
            "swellHeight": {
                "sg": 0.88
            },
            "swellPeriod": {
                "sg": 4.94
            },
            "time": "2026-01-29T01:00:00+00:00"
        },
        {
            "swellDirection": {
                "sg": 58.05
            },
            "swellHeight": {
                "sg": 0.83
            },
            "swellPeriod": {
                "sg": 4.98
            },
            "time": "2026-01-29T02:00:00+00:00"
        },
        {
            "swellDirection": {
                "sg": 58.69
            },
            "swellHeight": {
                "sg": 0.78
            },
            "swellPeriod": {
                "sg": 5.02
            },
            "time": "2026-01-29T03:00:00+00:00"
        },
        {
            "swellDirection": {
                "sg": 77.89
            },
            "swellHeight": {
                "sg": 0.73
            },
            "swellPeriod": {
                "sg": 5.56
            },
            "time": "2026-01-29T04:00:00+00:00"
        },
        {
            "swellDirection": {
                "sg": 97.1
            },
            "swellHeight": {
                "sg": 0.67
            },
            "swellPeriod": {
                "sg": 6.11
            },
            "time": "2026-01-29T05:00:00+00:00"
        },
        {
            "swellDirection": {
                "sg": 116.3
            },
            "swellHeight": {
                "sg": 0.62
            },
            "swellPeriod": {
                "sg": 6.65
            },
            "time": "2026-01-29T06:00:00+00:00"
        },
        {
            "swellDirection": {
                "sg": 141.44
            },
            "swellHeight": {
                "sg": 0.72
            },
            "swellPeriod": {
                "sg": 6.24
            },
            "time": "2026-01-29T07:00:00+00:00"
        },
        {
            "swellDirection": {
                "sg": 166.57
            },
            "swellHeight": {
                "sg": 0.81
            },
            "swellPeriod": {
                "sg": 5.84
            },
            "time": "2026-01-29T08:00:00+00:00"
        },
        {
            "swellDirection": {
                "sg": 191.71
            },
            "swellHeight": {
                "sg": 0.91
            },
            "swellPeriod": {
                "sg": 5.43
            },
            "time": "2026-01-29T09:00:00+00:00"
        },
        {
            "swellDirection": {
                "sg": 190.15
            },
            "swellHeight": {
                "sg": 1.04
            },
            "swellPeriod": {
                "sg": 5.39
            },
            "time": "2026-01-29T10:00:00+00:00"
        },
        {
            "swellDirection": {
                "sg": 188.59
            },
            "swellHeight": {
                "sg": 1.16
            },
            "swellPeriod": {
                "sg": 5.36
            },
            "time": "2026-01-29T11:00:00+00:00"
        },
        {
            "swellDirection": {
                "sg": 187.03
            },
            "swellHeight": {
                "sg": 1.29
            },
            "swellPeriod": {
                "sg": 5.32
            },
            "time": "2026-01-29T12:00:00+00:00"
        },
        {
            "swellDirection": {
                "sg": 185.29
            },
            "swellHeight": {
                "sg": 1.32
            },
            "swellPeriod": {
                "sg": 5.47
            },
            "time": "2026-01-29T13:00:00+00:00"
        },
        {
            "swellDirection": {
                "sg": 183.56
            },
            "swellHeight": {
                "sg": 1.36
            },
            "swellPeriod": {
                "sg": 5.62
            },
            "time": "2026-01-29T14:00:00+00:00"
        },
        {
            "swellDirection": {
                "sg": 181.82
            },
            "swellHeight": {
                "sg": 1.39
            },
            "swellPeriod": {
                "sg": 5.77
            },
            "time": "2026-01-29T15:00:00+00:00"
        },
        {
            "swellDirection": {
                "sg": 180.17
            },
            "swellHeight": {
                "sg": 1.39
            },
            "swellPeriod": {
                "sg": 5.85
            },
            "time": "2026-01-29T16:00:00+00:00"
        },
        {
            "swellDirection": {
                "sg": 178.51
            },
            "swellHeight": {
                "sg": 1.38
            },
            "swellPeriod": {
                "sg": 5.92
            },
            "time": "2026-01-29T17:00:00+00:00"
        },
        {
            "swellDirection": {
                "sg": 176.86
            },
            "swellHeight": {
                "sg": 1.38
            },
            "swellPeriod": {
                "sg": 6.0
            },
            "time": "2026-01-29T18:00:00+00:00"
        },
        {
            "swellDirection": {
                "sg": 175.77
            },
            "swellHeight": {
                "sg": 1.36
            },
            "swellPeriod": {
                "sg": 6.03
            },
            "time": "2026-01-29T19:00:00+00:00"
        },
        {
            "swellDirection": {
                "sg": 174.68
            },
            "swellHeight": {
                "sg": 1.33
            },
            "swellPeriod": {
                "sg": 6.07
            },
            "time": "2026-01-29T20:00:00+00:00"
        },
        {
            "swellDirection": {
                "sg": 173.59
            },
            "swellHeight": {
                "sg": 1.31
            },
            "swellPeriod": {
                "sg": 6.1
            },
            "time": "2026-01-29T21:00:00+00:00"
        },
        {
            "swellDirection": {
                "sg": 174.97
            },
            "swellHeight": {
                "sg": 1.22
            },
            "swellPeriod": {
                "sg": 6.19
            },
            "time": "2026-01-29T22:00:00+00:00"
        },
        {
            "swellDirection": {
                "sg": 176.35
            },
            "swellHeight": {
                "sg": 1.14
            },
            "swellPeriod": {
                "sg": 6.27
            },
            "time": "2026-01-29T23:00:00+00:00"
        },
        {
            "swellDirection": {
                "sg": 177.73
            },
            "swellHeight": {
                "sg": 1.05
            },
            "swellPeriod": {
                "sg": 6.36
            },
            "time": "2026-01-30T00:00:00+00:00"
        },
        {
            "swellDirection": {
                "sg": 173.32
            },
            "swellHeight": {
                "sg": 1.03
            },
            "swellPeriod": {
                "sg": 6.15
            },
            "time": "2026-01-30T01:00:00+00:00"
        },
        {
            "swellDirection": {
                "sg": 168.92
            },
            "swellHeight": {
                "sg": 1.01
            },
            "swellPeriod": {
                "sg": 5.94
            },
            "time": "2026-01-30T02:00:00+00:00"
        },
        {
            "swellDirection": {
                "sg": 164.51
            },
            "swellHeight": {
                "sg": 0.99
            },
            "swellPeriod": {
                "sg": 5.73
            },
            "time": "2026-01-30T03:00:00+00:00"
        },
        {
            "swellDirection": {
                "sg": 164.18
            },
            "swellHeight": {
                "sg": 0.99
            },
            "swellPeriod": {
                "sg": 5.81
            },
            "time": "2026-01-30T04:00:00+00:00"
        },
        {
            "swellDirection": {
                "sg": 163.85
            },
            "swellHeight": {
                "sg": 0.98
            },
            "swellPeriod": {
                "sg": 5.9
            },
            "time": "2026-01-30T05:00:00+00:00"
        },
        {
            "swellDirection": {
                "sg": 163.52
            },
            "swellHeight": {
                "sg": 0.98
            },
            "swellPeriod": {
                "sg": 5.98
            },
            "time": "2026-01-30T06:00:00+00:00"
        },
        {
            "swellDirection": {
                "sg": 163.43
            },
            "swellHeight": {
                "sg": 0.98
            },
            "swellPeriod": {
                "sg": 6.1
            },
            "time": "2026-01-30T07:00:00+00:00"
        },
        {
            "swellDirection": {
                "sg": 163.35
            },
            "swellHeight": {
                "sg": 0.97
            },
            "swellPeriod": {
                "sg": 6.22
            },
            "time": "2026-01-30T08:00:00+00:00"
        },
        {
            "swellDirection": {
                "sg": 163.26
            },
            "swellHeight": {
                "sg": 0.97
            },
            "swellPeriod": {
                "sg": 6.34
            },
            "time": "2026-01-30T09:00:00+00:00"
        },
        {
            "swellDirection": {
                "sg": 161.69
            },
            "swellHeight": {
                "sg": 0.92
            },
            "swellPeriod": {
                "sg": 6.3
            },
            "time": "2026-01-30T10:00:00+00:00"
        },
        {
            "swellDirection": {
                "sg": 160.12
            },
            "swellHeight": {
                "sg": 0.88
            },
            "swellPeriod": {
                "sg": 6.26
            },
            "time": "2026-01-30T11:00:00+00:00"
        },
        {
            "swellDirection": {
                "sg": 158.55
            },
            "swellHeight": {
                "sg": 0.83
            },
            "swellPeriod": {
                "sg": 6.22
            },
            "time": "2026-01-30T12:00:00+00:00"
        },
        {
            "swellDirection": {
                "sg": 132.15
            },
            "swellHeight": {
                "sg": 0.79
            },
            "swellPeriod": {
                "sg": 5.75
            },
            "time": "2026-01-30T13:00:00+00:00"
        },
        {
            "swellDirection": {
                "sg": 105.74
            },
            "swellHeight": {
                "sg": 0.76
            },
            "swellPeriod": {
                "sg": 5.29
            },
            "time": "2026-01-30T14:00:00+00:00"
        },
        {
            "swellDirection": {
                "sg": 79.34
            },
            "swellHeight": {
                "sg": 0.72
            },
            "swellPeriod": {
                "sg": 4.82
            },
            "time": "2026-01-30T15:00:00+00:00"
        },
        {
            "swellDirection": {
                "sg": 75.66
            },
            "swellHeight": {
                "sg": 0.8
            },
            "swellPeriod": {
                "sg": 4.83
            },
            "time": "2026-01-30T16:00:00+00:00"
        },
        {
            "swellDirection": {
                "sg": 71.99
            },
            "swellHeight": {
                "sg": 0.89
            },
            "swellPeriod": {
                "sg": 4.85
            },
            "time": "2026-01-30T17:00:00+00:00"
        },
        {
            "swellDirection": {
                "sg": 68.31
            },
            "swellHeight": {
                "sg": 0.97
            },
            "swellPeriod": {
                "sg": 4.86
            },
            "time": "2026-01-30T18:00:00+00:00"
        },
        {
            "swellDirection": {
                "sg": 65.46
            },
            "swellHeight": {
                "sg": 1.0
            },
            "swellPeriod": {
                "sg": 4.87
            },
            "time": "2026-01-30T19:00:00+00:00"
        },
        {
            "swellDirection": {
                "sg": 62.6
            },
            "swellHeight": {
                "sg": 1.04
            },
            "swellPeriod": {
                "sg": 4.89
            },
            "time": "2026-01-30T20:00:00+00:00"
        },
        {
            "swellDirection": {
                "sg": 59.75
            },
            "swellHeight": {
                "sg": 1.07
            },
            "swellPeriod": {
                "sg": 4.9
            },
            "time": "2026-01-30T21:00:00+00:00"
        },
        {
            "swellDirection": {
                "sg": 58.58
            },
            "swellHeight": {
                "sg": 1.08
            },
            "swellPeriod": {
                "sg": 4.87
            },
            "time": "2026-01-30T22:00:00+00:00"
        },
        {
            "swellDirection": {
                "sg": 57.42
            },
            "swellHeight": {
                "sg": 1.08
            },
            "swellPeriod": {
                "sg": 4.84
            },
            "time": "2026-01-30T23:00:00+00:00"
        }
    ],
    "meta": {
        "cost": 1,
        "dailyQuota": 10,
        "end": "2026-01-30 23:00",
        "lat": -33.8908,
        "lng": 151.2773,
        "params": [
            "swellDirection",
            "swellHeight",
            "swellPeriod"
        ],
        "requestCount": 1,
        "source": [
            "sg"
        ],
        "start": "2026-01-21 00:00"
    },
    "last_updated": "2026-01-22 06:28:09"
}